agnost/__init__.py
agnost/adapters.py
agnost/client.py
agnost/events.py
agnost/session.py
agnost/types.py
agnost/utils.py
agnost-0.1.8.dist-info/METADATA
agnost-0.1.8.dist-info/WHEEL
agnost-0.1.8.dist-info/top_level.txt
agnost-0.1.8.dist-info/RECORD
