Metadata-Version: 2.4
Name: agnost
Version: 0.1.8
Summary: Analytics SDK for Model Context Protocol Servers
Home-page: https://github.com/agnostai/agnostai
Author: Agnost AI
Author-email: Agnost AI <founders@agnost.ai>
License: MIT
Project-URL: Homepage, https://agnost.ai
Project-URL: BugTracker, https://docs.agnost.ai
Classifier: Programming Language :: Python :: 3
Classifier: Operating System :: OS Independent
Requires-Python: >=3.7
Requires-Dist: requests>=2.25.0
Provides-Extra: dev
Requires-Dist: pytest>=6.0; extra == "dev"
Dynamic: author
Dynamic: home-page
Dynamic: requires-python
